[
    {
        "entityID": 1,
        "phoneID": 1,
        "phoneTypeID": 1
    },
    {
        "entityID": 2,
        "phoneID": 2,
        "phoneTypeID": 1
    },
    {
        "entityID": 2,
        "phoneID": 3,
        "phoneTypeID": 2
    },
    {
        "entityID": 3,
        "phoneID": 4,
        "phoneTypeID": 1
    },
    {
        "entityID": 3,
        "phoneID": 5,
        "phoneTypeID": 2
    },
    {
        "entityID": 4,
        "phoneID": 6,
        "phoneTypeID": 1
    }
]
